README.rst
setup.cfg
setup.py
sp_yt_search/Singleton.py
sp_yt_search/__init__.py
sp_yt_search.egg-info/PKG-INFO
sp_yt_search.egg-info/SOURCES.txt
sp_yt_search.egg-info/dependency_links.txt
sp_yt_search.egg-info/requires.txt
sp_yt_search.egg-info/top_level.txt
sp_yt_search/SpSearch/Sp.py
sp_yt_search/SpSearch/SpAuth.py
sp_yt_search/SpSearch/SpObjects.py
sp_yt_search/SpSearch/SpSearchAlbum.py
sp_yt_search/SpSearch/SpSearchArtist.py
sp_yt_search/SpSearch/SpSearchPlaylist.py
sp_yt_search/SpSearch/SpSearchTrack.py
sp_yt_search/SpSearch/SpSettings.py
sp_yt_search/SpSearch/__init__.py
sp_yt_search/YtSearch/Helpers.py
sp_yt_search/YtSearch/YtObjects.py
sp_yt_search/YtSearch/YtSettings.py
sp_yt_search/YtSearch/__init__.py