Metadata-Version: 2.1
Name: sp-yt-search
Version: 1.0.2
Summary: Parse Spotify URI to youtube link
Home-page: https://github.com/MarcinMysliwiec/sp_yt_searcher
Author: Marcin Myśliwiec
Author-email: marcin.mysliw@gmail.com
License: MIT
Download-URL: https://github.com/MarcinMysliwiec/sp_yt_searcher/blob/master/dist/sp_yt_search-1.0.2.tar.gz
Keywords: sp_yt_search,yt,sp
Platform: UNKNOWN
Classifier: Development Status :: 5 - Production/Stable
Classifier: Intended Audience :: Developers
Classifier: Topic :: Software Development :: Build Tools
Classifier: License :: OSI Approved :: MIT License
Classifier: Programming Language :: Python :: 3
Classifier: Programming Language :: Python :: 3.4
Classifier: Programming Language :: Python :: 3.5
Classifier: Programming Language :: Python :: 3.6
Classifier: Programming Language :: Python :: 3.7
Classifier: Programming Language :: Python :: 3.8
